pptestdenislepkowski/__init__.py
pptestdenislepkowski/m_mod_pptest.py
pptestdenislepkowski-0.0.1.dist-info/LICENSE.txt
pptestdenislepkowski-0.0.1.dist-info/METADATA
pptestdenislepkowski-0.0.1.dist-info/WHEEL
pptestdenislepkowski-0.0.1.dist-info/top_level.txt
pptestdenislepkowski-0.0.1.dist-info/RECORD
