Metadata-Version: 2.1
Name: pptestdenislepkowski
Version: 0.0.1
Summary: My test package
Author-email: DL <test@test.pl>
License: MIT License
Keywords: pptestdenislepkowski,funny functions,name,surname,personal data
Classifier: Framework :: IDLE
Classifier: License :: Free For Educational Use
Requires-Python: >=3.0
License-File: LICENSE.txt
Requires-Dist: numpy ; python_version >= "3.0"
